{
  "created_at": "2025-08-19T14:46:13.352813",
  "ttl_hours": 12,
  "cache_key": "db_with_anchor_3053b816e511e6f6c55014cb84f4c445",
  "data": [
    {
      "FinancialInstrumentFundValueHistoryId": 2121693,
      "FinancialInstrumentId": 771,
      "QuotaValue": "2.41510250",
      "Name": "PORTO SEGURO JURO REAL FIRF LP",
      "PositionDate": "2024-12-31 00:00:00",
      "PeriodoSelecionado": 2,
      "DescricaoPeriodo": "AnoAtual",
      "DataInicioPeriodo": "2025-01-01",
      "DataFimPeriodo": "2025-12-31"
    },
    {
      "FinancialInstrumentFundValueHistoryId": 2122414,
      "FinancialInstrumentId": 771,
      "QuotaValue": "2.42575480",
      "Name": "PORTO SEGURO JURO REAL FIRF LP",
      "PositionDate": "2025-01-02 00:00:00",
      "PeriodoSelecionado": 2,
      "DescricaoPeriodo": "AnoAtual",
      "DataInicioPeriodo": "2025-01-01",
      "DataFimPeriodo": "2025-12-31"
    },
    {
      "FinancialInstrumentFundValueHistoryId": 2123109,
      "FinancialInstrumentId": 771,
      "QuotaValue": "2.43066050",
      "Name": "PORTO SEGURO JURO REAL FIRF LP",
      "PositionDate": "2025-01-03 00:00:00",
      "PeriodoSelecionado": 2,
      "DescricaoPeriodo": "AnoAtual",
      "DataInicioPeriodo": "2025-01-01",
      "DataFimPeriodo": "2025-12-31"
    },
    {
      "FinancialInstrumentFundValueHistoryId": 2123973,
      "FinancialInstrumentId": 771,
      "QuotaValue": "2.44199980",
      "Name": "PORTO SEGURO JURO REAL FIRF LP",
      "PositionDate": "2025-01-06 00:00:00",
      "PeriodoSelecionado": 2,
      "DescricaoPeriodo": "AnoAtual",
      "DataInicioPeriodo": "2025-01-01",
      "DataFimPeriodo": "2025-12-31"
    },
    {
      "FinancialInstrumentFundValueHistoryId": 2124635,
      "FinancialInstrumentId": 771,
      "QuotaValue": "2.44072210",
      "Name": "PORTO SEGURO JURO REAL FIRF LP",
      "PositionDate": "2025-01-07 00:00:00",
      "PeriodoSelecionado": 2,
      "DescricaoPeriodo": "AnoAtual",
      "DataInicioPeriodo": "2025-01-01",
      "DataFimPeriodo": "2025-12-31"
    },
    {
      "FinancialInstrumentFundValueHistoryId": 2125316,
      "FinancialInstrumentId": 771,
      "QuotaValue": "2.44339170",
      "Name": "PORTO SEGURO JURO REAL FIRF LP",
      "PositionDate": "2025-01-08 00:00:00",
      "PeriodoSelecionado": 2,
      "DescricaoPeriodo": "AnoAtual",
      "DataInicioPeriodo": "2025-01-01",
      "DataFimPeriodo": "2025-12-31"
    },
    {
      "FinancialInstrumentFundValueHistoryId": 2125956,
      "FinancialInstrumentId": 771,
      "QuotaValue": "2.44337650",
      "Name": "PORTO SEGURO JURO REAL FIRF LP",
      "PositionDate": "2025-01-09 00:00:00",
      "PeriodoSelecionado": 2,
      "DescricaoPeriodo": "AnoAtual",
      "DataInicioPeriodo": "2025-01-01",
      "DataFimPeriodo": "2025-12-31"
    },
    {
      "FinancialInstrumentFundValueHistoryId": 2127029,
      "FinancialInstrumentId": 771,
      "QuotaValue": "2.43628580",
      "Name": "PORTO SEGURO JURO REAL FIRF LP",
      "PositionDate": "2025-01-10 00:00:00",
      "PeriodoSelecionado": 2,
      "DescricaoPeriodo": "AnoAtual",
      "DataInicioPeriodo": "2025-01-01",
      "DataFimPeriodo": "2025-12-31"
    },
    {
      "FinancialInstrumentFundValueHistoryId": 2127449,
      "FinancialInstrumentId": 771,
      "QuotaValue": "2.43123910",
      "Name": "PORTO SEGURO JURO REAL FIRF LP",
      "PositionDate": "2025-01-13 00:00:00",
      "PeriodoSelecionado": 2,
      "DescricaoPeriodo": "AnoAtual",
      "DataInicioPeriodo": "2025-01-01",
      "DataFimPeriodo": "2025-12-31"
    },
    {
      "FinancialInstrumentFundValueHistoryId": 2128008,
      "FinancialInstrumentId": 771,
      "QuotaValue": "2.43801240",
      "Name": "PORTO SEGURO JURO REAL FIRF LP",
      "PositionDate": "2025-01-14 00:00:00",
      "PeriodoSelecionado": 2,
      "DescricaoPeriodo": "AnoAtual",
      "DataInicioPeriodo": "2025-01-01",
      "DataFimPeriodo": "2025-12-31"
    },
    {
      "FinancialInstrumentFundValueHistoryId": 2128543,
      "FinancialInstrumentId": 771,
      "QuotaValue": "2.44569000",
      "Name": "PORTO SEGURO JURO REAL FIRF LP",
      "PositionDate": "2025-01-15 00:00:00",
      "PeriodoSelecionado": 2,
      "DescricaoPeriodo": "AnoAtual",
      "DataInicioPeriodo": "2025-01-01",
      "DataFimPeriodo": "2025-12-31"
    },
    {
      "FinancialInstrumentFundValueHistoryId": 2129198,
      "FinancialInstrumentId": 771,
      "QuotaValue": "2.43981120",
      "Name": "PORTO SEGURO JURO REAL FIRF LP",
      "PositionDate": "2025-01-16 00:00:00",
      "PeriodoSelecionado": 2,
      "DescricaoPeriodo": "AnoAtual",
      "DataInicioPeriodo": "2025-01-01",
      "DataFimPeriodo": "2025-12-31"
    },
    {
      "FinancialInstrumentFundValueHistoryId": 2130234,
      "FinancialInstrumentId": 771,
      "QuotaValue": "2.43083460",
      "Name": "PORTO SEGURO JURO REAL FIRF LP",
      "PositionDate": "2025-01-17 00:00:00",
      "PeriodoSelecionado": 2,
      "DescricaoPeriodo": "AnoAtual",
      "DataInicioPeriodo": "2025-01-01",
      "DataFimPeriodo": "2025-12-31"
    },
    {
      "FinancialInstrumentFundValueHistoryId": 2130684,
      "FinancialInstrumentId": 771,
      "QuotaValue": "2.42560130",
      "Name": "PORTO SEGURO JURO REAL FIRF LP",
      "PositionDate": "2025-01-20 00:00:00",
      "PeriodoSelecionado": 2,
      "DescricaoPeriodo": "AnoAtual",
      "DataInicioPeriodo": "2025-01-01",
      "DataFimPeriodo": "2025-12-31"
    },
    {
      "FinancialInstrumentFundValueHistoryId": 2131203,
      "FinancialInstrumentId": 771,
      "QuotaValue": "2.41567890",
      "Name": "PORTO SEGURO JURO REAL FIRF LP",
      "PositionDate": "2025-01-21 00:00:00",
      "PeriodoSelecionado": 2,
      "DescricaoPeriodo": "AnoAtual",
      "DataInicioPeriodo": "2025-01-01",
      "DataFimPeriodo": "2025-12-31"
    },
    {
      "FinancialInstrumentFundValueHistoryId": 2131839,
      "FinancialInstrumentId": 771,
      "QuotaValue": "2.41820360",
      "Name": "PORTO SEGURO JURO REAL FIRF LP",
      "PositionDate": "2025-01-22 00:00:00",
      "PeriodoSelecionado": 2,
      "DescricaoPeriodo": "AnoAtual",
      "DataInicioPeriodo": "2025-01-01",
      "DataFimPeriodo": "2025-12-31"
    },
    {
      "FinancialInstrumentFundValueHistoryId": 2132671,
      "FinancialInstrumentId": 771,
      "QuotaValue": "2.41316510",
      "Name": "PORTO SEGURO JURO REAL FIRF LP",
      "PositionDate": "2025-01-23 00:00:00",
      "PeriodoSelecionado": 2,
      "DescricaoPeriodo": "AnoAtual",
      "DataInicioPeriodo": "2025-01-01",
      "DataFimPeriodo": "2025-12-31"
    },
    {
      "FinancialInstrumentFundValueHistoryId": 2133294,
      "FinancialInstrumentId": 771,
      "QuotaValue": "2.41953600",
      "Name": "PORTO SEGURO JURO REAL FIRF LP",
      "PositionDate": "2025-01-24 00:00:00",
      "PeriodoSelecionado": 2,
      "DescricaoPeriodo": "AnoAtual",
      "DataInicioPeriodo": "2025-01-01",
      "DataFimPeriodo": "2025-12-31"
    },
    {
      "FinancialInstrumentFundValueHistoryId": 2133995,
      "FinancialInstrumentId": 771,
      "QuotaValue": "2.41977170",
      "Name": "PORTO SEGURO JURO REAL FIRF LP",
      "PositionDate": "2025-01-27 00:00:00",
      "PeriodoSelecionado": 2,
      "DescricaoPeriodo": "AnoAtual",
      "DataInicioPeriodo": "2025-01-01",
      "DataFimPeriodo": "2025-12-31"
    },
    {
      "FinancialInstrumentFundValueHistoryId": 2134644,
      "FinancialInstrumentId": 771,
      "QuotaValue": "2.42104750",
      "Name": "PORTO SEGURO JURO REAL FIRF LP",
      "PositionDate": "2025-01-28 00:00:00",
      "PeriodoSelecionado": 2,
      "DescricaoPeriodo": "AnoAtual",
      "DataInicioPeriodo": "2025-01-01",
      "DataFimPeriodo": "2025-12-31"
    },
    {
      "FinancialInstrumentFundValueHistoryId": 2135237,
      "FinancialInstrumentId": 771,
      "QuotaValue": "2.41942770",
      "Name": "PORTO SEGURO JURO REAL FIRF LP",
      "PositionDate": "2025-01-29 00:00:00",
      "PeriodoSelecionado": 2,
      "DescricaoPeriodo": "AnoAtual",
      "DataInicioPeriodo": "2025-01-01",
      "DataFimPeriodo": "2025-12-31"
    },
    {
      "FinancialInstrumentFundValueHistoryId": 2135908,
      "FinancialInstrumentId": 771,
      "QuotaValue": "2.45164980",
      "Name": "PORTO SEGURO JURO REAL FIRF LP",
      "PositionDate": "2025-01-30 00:00:00",
      "PeriodoSelecionado": 2,
      "DescricaoPeriodo": "AnoAtual",
      "DataInicioPeriodo": "2025-01-01",
      "DataFimPeriodo": "2025-12-31"
    },
    {
      "FinancialInstrumentFundValueHistoryId": 2136608,
      "FinancialInstrumentId": 771,
      "QuotaValue": "2.44784770",
      "Name": "PORTO SEGURO JURO REAL FIRF LP",
      "PositionDate": "2025-01-31 00:00:00",
      "PeriodoSelecionado": 2,
      "DescricaoPeriodo": "AnoAtual",
      "DataInicioPeriodo": "2025-01-01",
      "DataFimPeriodo": "2025-12-31"
    },
    {
      "FinancialInstrumentFundValueHistoryId": 2137548,
      "FinancialInstrumentId": 771,
      "QuotaValue": "2.45694910",
      "Name": "PORTO SEGURO JURO REAL FIRF LP",
      "PositionDate": "2025-02-03 00:00:00",
      "PeriodoSelecionado": 2,
      "DescricaoPeriodo": "AnoAtual",
      "DataInicioPeriodo": "2025-01-01",
      "DataFimPeriodo": "2025-12-31"
    },
    {
      "FinancialInstrumentFundValueHistoryId": 2138192,
      "FinancialInstrumentId": 771,
      "QuotaValue": "2.45151720",
      "Name": "PORTO SEGURO JURO REAL FIRF LP",
      "PositionDate": "2025-02-04 00:00:00",
      "PeriodoSelecionado": 2,
      "DescricaoPeriodo": "AnoAtual",
      "DataInicioPeriodo": "2025-01-01",
      "DataFimPeriodo": "2025-12-31"
    },
    {
      "FinancialInstrumentFundValueHistoryId": 2138849,
      "FinancialInstrumentId": 771,
      "QuotaValue": "2.44325520",
      "Name": "PORTO SEGURO JURO REAL FIRF LP",
      "PositionDate": "2025-02-05 00:00:00",
      "PeriodoSelecionado": 2,
      "DescricaoPeriodo": "AnoAtual",
      "DataInicioPeriodo": "2025-01-01",
      "DataFimPeriodo": "2025-12-31"
    },
    {
      "FinancialInstrumentFundValueHistoryId": 2139496,
      "FinancialInstrumentId": 771,
      "QuotaValue": "2.44785870",
      "Name": "PORTO SEGURO JURO REAL FIRF LP",
      "PositionDate": "2025-02-06 00:00:00",
      "PeriodoSelecionado": 2,
      "DescricaoPeriodo": "AnoAtual",
      "DataInicioPeriodo": "2025-01-01",
      "DataFimPeriodo": "2025-12-31"
    },
    {
      "FinancialInstrumentFundValueHistoryId": 2140188,
      "FinancialInstrumentId": 771,
      "QuotaValue": "2.44657080",
      "Name": "PORTO SEGURO JURO REAL FIRF LP",
      "PositionDate": "2025-02-07 00:00:00",
      "PeriodoSelecionado": 2,
      "DescricaoPeriodo": "AnoAtual",
      "DataInicioPeriodo": "2025-01-01",
      "DataFimPeriodo": "2025-12-31"
    },
    {
      "FinancialInstrumentFundValueHistoryId": 2140884,
      "FinancialInstrumentId": 771,
      "QuotaValue": "2.44724220",
      "Name": "PORTO SEGURO JURO REAL FIRF LP",
      "PositionDate": "2025-02-10 00:00:00",
      "PeriodoSelecionado": 2,
      "DescricaoPeriodo": "AnoAtual",
      "DataInicioPeriodo": "2025-01-01",
      "DataFimPeriodo": "2025-12-31"
    },
    {
      "FinancialInstrumentFundValueHistoryId": 2141800,
      "FinancialInstrumentId": 771,
      "QuotaValue": "2.45239870",
      "Name": "PORTO SEGURO JURO REAL FIRF LP",
      "PositionDate": "2025-02-11 00:00:00",
      "PeriodoSelecionado": 2,
      "DescricaoPeriodo": "AnoAtual",
      "DataInicioPeriodo": "2025-01-01",
      "DataFimPeriodo": "2025-12-31"
    },
    {
      "FinancialInstrumentFundValueHistoryId": 2142458,
      "FinancialInstrumentId": 771,
      "QuotaValue": "2.45014530",
      "Name": "PORTO SEGURO JURO REAL FIRF LP",
      "PositionDate": "2025-02-12 00:00:00",
      "PeriodoSelecionado": 2,
      "DescricaoPeriodo": "AnoAtual",
      "DataInicioPeriodo": "2025-01-01",
      "DataFimPeriodo": "2025-12-31"
    },
    {
      "FinancialInstrumentFundValueHistoryId": 2143087,
      "FinancialInstrumentId": 771,
      "QuotaValue": "2.45461720",
      "Name": "PORTO SEGURO JURO REAL FIRF LP",
      "PositionDate": "2025-02-13 00:00:00",
      "PeriodoSelecionado": 2,
      "DescricaoPeriodo": "AnoAtual",
      "DataInicioPeriodo": "2025-01-01",
      "DataFimPeriodo": "2025-12-31"
    },
    {
      "FinancialInstrumentFundValueHistoryId": 2143755,
      "FinancialInstrumentId": 771,
      "QuotaValue": "2.47461900",
      "Name": "PORTO SEGURO JURO REAL FIRF LP",
      "PositionDate": "2025-02-14 00:00:00",
      "PeriodoSelecionado": 2,
      "DescricaoPeriodo": "AnoAtual",
      "DataInicioPeriodo": "2025-01-01",
      "DataFimPeriodo": "2025-12-31"
    },
    {
      "FinancialInstrumentFundValueHistoryId": 2144400,
      "FinancialInstrumentId": 771,
      "QuotaValue": "2.48616280",
      "Name": "PORTO SEGURO JURO REAL FIRF LP",
      "PositionDate": "2025-02-17 00:00:00",
      "PeriodoSelecionado": 2,
      "DescricaoPeriodo": "AnoAtual",
      "DataInicioPeriodo": "2025-01-01",
      "DataFimPeriodo": "2025-12-31"
    },
    {
      "FinancialInstrumentFundValueHistoryId": 2146209,
      "FinancialInstrumentId": 771,
      "QuotaValue": "2.48513370",
      "Name": "PORTO SEGURO JURO REAL FIRF LP",
      "PositionDate": "2025-02-18 00:00:00",
      "PeriodoSelecionado": 2,
      "DescricaoPeriodo": "AnoAtual",
      "DataInicioPeriodo": "2025-01-01",
      "DataFimPeriodo": "2025-12-31"
    },
    {
      "FinancialInstrumentFundValueHistoryId": 2146908,
      "FinancialInstrumentId": 771,
      "QuotaValue": "2.48118840",
      "Name": "PORTO SEGURO JURO REAL FIRF LP",
      "PositionDate": "2025-02-19 00:00:00",
      "PeriodoSelecionado": 2,
      "DescricaoPeriodo": "AnoAtual",
      "DataInicioPeriodo": "2025-01-01",
      "DataFimPeriodo": "2025-12-31"
    },
    {
      "FinancialInstrumentFundValueHistoryId": 2147528,
      "FinancialInstrumentId": 771,
      "QuotaValue": "2.48517190",
      "Name": "PORTO SEGURO JURO REAL FIRF LP",
      "PositionDate": "2025-02-20 00:00:00",
      "PeriodoSelecionado": 2,
      "DescricaoPeriodo": "AnoAtual",
      "DataInicioPeriodo": "2025-01-01",
      "DataFimPeriodo": "2025-12-31"
    },
    {
      "FinancialInstrumentFundValueHistoryId": 2148179,
      "FinancialInstrumentId": 771,
      "QuotaValue": "2.49061470",
      "Name": "PORTO SEGURO JURO REAL FIRF LP",
      "PositionDate": "2025-02-21 00:00:00",
      "PeriodoSelecionado": 2,
      "DescricaoPeriodo": "AnoAtual",
      "DataInicioPeriodo": "2025-01-01",
      "DataFimPeriodo": "2025-12-31"
    }
  ]
}